{"cameraMode":{"drawMode":0,"name":"Shaded","section":"Shading Mode"},"sceneLighting":true,"audioPlay":false,"sceneViewState":{"m_AlwaysRefresh":false,"showFog":true,"showSkybox":true,"showFlares":true,"showImageEffects":true,"showParticleSystems":true,"showVisualEffectGraphs":true,"m_FxEnabled":true},"in2DMode":false,"pivot":{"x":715.20361328125,"y":-471.54266357421877,"z":1057.3543701171875},"rotation":{"x":0.35588786005973818,"y":0.13618530333042146,"z":-0.052465055137872699,"w":0.923082709312439},"size":744.5560302734375,"orthographic":false}